dlgt/__init__.py
dlgt-0.1.1.dist-info/METADATA
dlgt-0.1.1.dist-info/WHEEL
dlgt-0.1.1.dist-info/licenses/LICENSE
dlgt-0.1.1.dist-info/RECORD
